kamihi/__init__.py
kamihi/py.typed
kamihi/base/__init__.py
kamihi/base/config.py
kamihi/base/logging.py
kamihi/base/manual_send.py
kamihi/bot/__init__.py
kamihi/bot/action.py
kamihi/bot/bot.py
kamihi/bot/utils.py
kamihi/cli/__init__.py
kamihi/cli/cli.py
kamihi/cli/utils.py
kamihi/cli/commands/__init__.py
kamihi/cli/commands/action.py
kamihi/cli/commands/db.py
kamihi/cli/commands/init.py
kamihi/cli/commands/permission.py
kamihi/cli/commands/role.py
kamihi/cli/commands/run.py
kamihi/cli/commands/user.py
kamihi/cli/commands/version.py
kamihi/db/__init__.py
kamihi/db/db.py
kamihi/db/models.py
kamihi/tg/__init__.py
kamihi/tg/client.py
kamihi/tg/default_handlers.py
kamihi/tg/media.py
kamihi/tg/send.py
kamihi/tg/handlers/__init__.py
kamihi/tg/handlers/auth_handler.py
kamihi/users/__init__.py
kamihi/users/users.py
kamihi/web/__init__.py
kamihi/web/views.py
kamihi/web/web.py
kamihi/web/static/images/apple-touch-icon.png
kamihi/web/static/images/favicon.ico
kamihi/web/static/images/icon-192-maskable.png
kamihi/web/static/images/icon-192.png
kamihi/web/static/images/icon-512-maskable.png
kamihi/web/static/images/icon-512.png
kamihi/web/templates/home.html
kamihi-4.0.0.dist-info/METADATA
kamihi-4.0.0.dist-info/WHEEL
kamihi-4.0.0.dist-info/entry_points.txt
kamihi-4.0.0.dist-info/licenses/LICENSE.md
kamihi-4.0.0.dist-info/RECORD
